aeromiko/__init__.py
aeromiko/aeromiko.py
aeromiko/templates/__init__.py
aeromiko/templates/get_hostname.textfsm
aeromiko/templates/show_acsp.textfsm
aeromiko/templates/show_acsp_channel_info.textfsm
aeromiko/templates/show_acsp_neighbor.textfsm
aeromiko/templates/show_boot_param.textfsm
aeromiko/templates/show_capwap_client.textfsm
aeromiko/templates/show_clock.textfsm
aeromiko/templates/show_console.textfsm
aeromiko/templates/show_cpu.textfsm
aeromiko/templates/show_dns.textfsm
aeromiko/templates/show_eth.textfsm
aeromiko/templates/show_hivemanager.textfsm
aeromiko/templates/show_hw_info.textfsm
aeromiko/templates/show_idm.textfsm
aeromiko/templates/show_ip_route.textfsm
aeromiko/templates/show_lldp_neighbor.textfsm
aeromiko/templates/show_memory.textfsm
aeromiko/templates/show_ntp.textfsm
aeromiko/templates/show_route.textfsm
aeromiko/templates/show_snmp.textfsm
aeromiko/templates/show_ssid.textfsm
aeromiko/templates/show_station.textfsm
aeromiko/templates/show_temperature.textfsm
aeromiko/templates/show_timezone.textfsm
aeromiko/templates/show_version.textfsm
aeromiko/templates/show_wifi.textfsm
aeromiko-1.2.0.dist-info/LICENSE
aeromiko-1.2.0.dist-info/METADATA
aeromiko-1.2.0.dist-info/WHEEL
aeromiko-1.2.0.dist-info/top_level.txt
aeromiko-1.2.0.dist-info/RECORD
