Metadata-Version: 2.1
Name: aeromiko
Version: 1.2.0
Summary: Aeromiko is a middle-man script to simplify extracting data from Aerohive APs using Netmiko
Home-page: https://github.com/andytruett/aeromiko
Author: Andy Truett
Author-email: andrew.truett@gmail.com
License: MIT License
Download-URL: https://github.com/andytruett/Aeromiko/archive/1.1.2.tar.gz
Keywords: aerohive netmiko
Platform: UNKNOWN
Classifier: Programming Language :: Python :: 3
Classifier: License :: OSI Approved :: MIT License
Classifier: Operating System :: OS Independent
Requires-Dist: netmiko (>=2.4.0)
